cosmoplotian/__init__.py
cosmoplotian/_astropy_init.py
cosmoplotian/colormaps.py
cosmoplotian/conftest.py
cosmoplotian/data/README.rst
cosmoplotian/extern/__init__.py
cosmoplotian/projections.py
cosmoplotian/tests/__init__.py
cosmoplotian/tests/test_plots.py
cosmoplotian/utils/__init__.py
cosmoplotian/utils/tests/__init__.py
cosmoplotian-0.0.1.dist-info/WHEEL
cosmoplotian-0.0.1.dist-info/METADATA
cosmoplotian-0.0.1.dist-info/RECORD
